dragonchain_sdk/__init__.py
dragonchain_sdk/async_helpers.py
dragonchain_sdk/configuration.py
dragonchain_sdk/credentials.py
dragonchain_sdk/dragonchain_client.py
dragonchain_sdk/exceptions.py
dragonchain_sdk/py.typed
dragonchain_sdk/request.py
dragonchain_sdk/types.py
dragonchain_sdk-4.3.0.dist-info/LICENSE
dragonchain_sdk-4.3.0.dist-info/METADATA
dragonchain_sdk-4.3.0.dist-info/WHEEL
dragonchain_sdk-4.3.0.dist-info/top_level.txt
dragonchain_sdk-4.3.0.dist-info/RECORD
