Metadata-Version: 2.1
Name: dragonchain-sdk
Version: 4.3.0
Summary: Dragonchain SDK for Python
Home-page: https://dragonchain.com
Author: Dragonchain
Author-email: support@dragonchain.com
License: Apache License 2.0
Project-URL: Documentation, https://python-sdk-docs.dragonchain.com/latest/
Project-URL: Source, https://github.com/dragonchain/dragonchain-sdk-python
Project-URL: Bug Tracker, https://github.com/dragonchain/dragonchain-sdk-python/issues
Platform: UNKNOWN
Classifier: Development Status :: 5 - Production/Stable
Classifier: Intended Audience :: Developers
Classifier: License :: OSI Approved :: Apache Software License
Classifier: Operating System :: POSIX
Classifier: Operating System :: MacOS :: MacOS X
Classifier: Operating System :: Microsoft :: Windows
Classifier: Natural Language :: English
Classifier: Programming Language :: Python
Classifier: Programming Language :: Python :: 3
Classifier: Programming Language :: Python :: 3.4
Classifier: Programming Language :: Python :: 3.5
Classifier: Programming Language :: Python :: 3.6
Classifier: Programming Language :: Python :: 3.7
Classifier: Programming Language :: Python :: 3.8
Classifier: Programming Language :: Python :: 3 :: Only
Classifier: Programming Language :: Python :: Implementation :: CPython
Classifier: Programming Language :: Python :: Implementation :: PyPy
Classifier: Typing :: Typed
Requires-Python: >=3.4
Requires-Dist: requests (>=2.4.0)
Requires-Dist: typing ; python_version < "3.5"
Provides-Extra: aio
Requires-Dist: aiohttp (>=3.5.0) ; extra == 'aio'
